mutationtracker/__init__.py
mutationtracker/access.py
mutationtracker/caller.py
mutationtracker/ledger.py
mutationtracker/mutation.py
mutationtracker/mutation_tracked_object.py
mutationtracker/settings.py
mutationtracker/track_mutations_decorator.py
mutationtracker/utils.py
mutationtracker-1.0.1.dist-info/LICENSE
mutationtracker-1.0.1.dist-info/METADATA
mutationtracker-1.0.1.dist-info/WHEEL
mutationtracker-1.0.1.dist-info/top_level.txt
mutationtracker-1.0.1.dist-info/RECORD
