Metadata-Version: 2.2
Name: mutationtracker
Version: 1.0.1
Summary: Saving users from debug-hell by conveniently keeping track of mutations in objects and logging them
Home-page: https://github.com/RedmanLabs/mutationtracker
Author: Jaime Derrez
Author-email: mail@redmanlabs.nl
Keywords: mutation tracked object,mutationtrackedobject,mutation,mutations,mutation tracker,object tracker,object mutations,changelog,change tracker,object changes,observer pattern,object observer,change observer,mutation observer,log changes,mutation log,log mutations,trace change,attribute value
Classifier: Development Status :: 5 - Production/Stable
Classifier: Intended Audience :: Developers
Classifier: Natural Language :: English
Classifier: Topic :: Software Development :: Libraries
Classifier: Programming Language :: Python :: 3
Classifier: License :: OSI Approved :: BSD License
Classifier: Operating System :: OS Independent
Requires-Python: >=3.7
License-File: LICENSE
Dynamic: author
Dynamic: author-email
Dynamic: classifier
Dynamic: description
Dynamic: description-content-type
Dynamic: home-page
Dynamic: keywords
Dynamic: requires-python
Dynamic: summary
